Metadata-Version: 2.1
Name: retico-wav2vecasr
Version: 0.1.3
Summary: The Huggingface wav2vec ASR incremental modules for the retico framework
Home-page: https://github.com/retico-team/retico-wav2vecasr
Download-URL: https://github.com/retico-team/retico-wav2vecasr
Author: Tahsin Mir Imtiaz, Ryan Whetten, Casey Kennington, Thilo Michael
Author-email: caseykennington@boisestate.edu
Keywords: retico,framework,incremental,dialogue,dialog,asr,speech
Classifier: Development Status :: 2 - Pre-Alpha
Classifier: Programming Language :: Python :: 3
Classifier: License :: OSI Approved :: Apache Software License
License-File: LICENSE
